gcal_mcp/__init__.py
gcal_mcp-0.1.4.dist-info/WHEEL
gcal_mcp-0.1.4.dist-info/entry_points.txt
gcal_mcp-0.1.4.dist-info/METADATA
gcal_mcp-0.1.4.dist-info/RECORD
